{
    "openapi": "3.0.0",
    "info": {
        "title": "Library API",
        "version": "1.0.1",
        "description": "API for managing authors and books."
    },
    "servers": [
        {
            "url": "http://localhost:8080",
            "description": "Local development server"
        },
        {
            "url": "https://library2-api.onrender.com",
            "description": "Render production server"
        }
    ],
    "components":{
        "securitySchemes": {
          "bearerAuth": {
            "type": "http",
            "scheme": "bearer",
            "bearerFormat": "JWT"
        }
      }
    },


    "tags": [
        {
            "name": "Auth", "description": "Authentication  management operations"},
            {"name": "Authors", "description": "Author management"},
            {"name": "Books", "description": "Books management operations"}
        ],
    
    "paths": {
        "/auth/register": {
            "post": {
             "tags": ["Auth"],
             "summary": " Register a new user",
             "requestBody": {
            "required": true,
            "content": {
            "application/json": {
            "schema": {
            "type": "object",
            "required": ["username", "email", "password"],
            "properties": {
            "username": {
            "type": "string",
            "description": "Unique username"
            },
            "email": {
                "type": "string",
                "format": "email",
                "description": "User email address"
            },
            "password": {
                "type": "string",
                "minLength": 6,
                "description": "User password (minimum 6 characters)"
            }
           }
          },

            "example": {
                "username": "emmanuelowilli",
                "email": "emmanuelowilli2025@gmail.com",
                "password": "moroni10"
            }
           }
         }
       },
       "responses": {
        "201": { "description": "User registered successfully"},
        "400": { "description": "Validation error or user already exists"},
        "500": { " description": "Server error"}
       }
    }
},
"/auth/login": {
    "post": {
        "tags": ["Auth"],
        "summary": "Login user and receive JWT",
        "requestBody": {
            "required": true,
            "content": {
                "application/json": {
                    "schema": {
                        "type": "object",
                        "required": ["email", "password"],
                        "properties": {
                            "email": {
                                "type": "string",
                                "format": "email",
                                "description": "User email address"
                            },
                            "password": {
                              "type": "string",
                              "description": "User password"
                            }
                        }
                    },
                    "example": {
                      "email": "emmanuelowilli2025@gmail.com",
                      "password": "moroni10"
                    }
                }
            }
        },
        "responses": {
            "200": { "description": "JWT token returned" },
            "400": { "description": "Invalid credentials"},
            "500": { "description": "Server error"}
        }
    }
},
        "/api/authors": {
            "get": {
                "summary": "Get all authors",
                "tags": ["Authors"],
                 "security": [
                    {"bearerAuth": [] }
                ],
                "responses": {
                    "200": {
                        "description": "A list of authors"},
                    "500": {
                        "description": "Server error"}
                }
            },
           
            "post": {
                "summary": "Create a new author",
                "tags": ["Authors"],
                "security": [
                    {"bearerAuth": [] }
                ],
                "requestBody": {
                    "required": true,
                    "content": {
                        "application/json": {
                            "schema": {
                               "type": "object",
                               "required": ["firstname", "lastname", "birthDate"],
                                 "properties": {
                                      "firstName": {"type": "string"},
                                      "lastName": {"type": "string"},
                                      "birthDate": {"type": "string", "format": "date"}
                                 }
                            },
                            "example": {
                                "firstName": "Emma",
                                "lastName": "Smith",
                                "birthDate": "2000-10-25"
                            }
                        }
                    }
                },
                "responses": {
                    "201": {
                        "description": "Author created successfully"},
                    "400": {
                        "description": "Invalid input"},
                    "500": {
                        "description": "Server error"}
                }
            }
        },

        "/api/authors/{authorId}": {
            "get": {
                "summary": "Get author by ID",
                "tags": ["Authors"],
                 "security": [
                    {"bearerAuth": [] }
                ],
                "parameters": [
                    {
                        "name": "authorId",
                        "in": "path",
                        "required": true,
                        "schema": {
                            "type": "string"}
                    }
                ],
                "responses": {
                    "200": {
                        "description": "Author details"},
                    "404": {
                        "description": "Author not found"},
                    "500": {
                        "description": "Server error"}
                }
            },
            "put": {
                "summary": "Update author by ID",
                "tags": ["Authors"],
                "parameters": [
                    {
                        "name": "authorId",
                        "in": "path",
                        "required": true,
                        "schema": {
                            "type": "string"}
                    }
                ],
                "requestBody": {
                    "required": true,
                    "content": {
                        "application/json": {
                            "schema": {
                               "type": "object",
                               "required": ["firstName", "lastName", "birthDate"],
                               "properties": {
                                      "firstName": {"type": "string"},
                                      "lastName": {"type": "string"},
                                      "birthDate": {"type": "string", "format": "date"}
                                 }
                            },
                            "example": {
                                "firstName": "Emma",
                                "lastName": "Johnson",
                                "birthDate": "2000-10-25"
                            }
                        }
                    }
                },
                "responses": {
                    "200": {
                        "description": "Author updated successfully"},
                    "400": {
                        "description": "Invalid input"},
                    "404": {
                        "description": "Author not found"},
                    "500": {
                        "description": "Server error"}
                }
            },
            "delete": {
                "summary": "Delete author by ID",
                "tags": ["Authors"],
                 "security": [
                    {"bearerAuth": [] }
                ],
                "parameters": [
                    {
                        "name": "authorId",
                        "in": "path",
                        "required": true,
                        "schema": {
                            "type": "string"}
                    }
                ],
                "responses": {
                    "204": {
                        "description": "Author deleted successfully"},
                    "404": {
                        "description": "Author not found"},
                    "500": {
                        "description": "Server error"}
                }
            }
        },

        "/api/books": {
            "get": {
                "summary": "Get all books",
                "tags": ["Books"],
                 "security": [
                    {"bearerAuth": [] }
                ],
                "responses": {
                    "200": {
                        "description": "A list of books"},
                    "500": {
                        "description": "Server error"}
                }
            },
            "post": {
                "summary": "Create a new book",
                "tags": ["Books"],
                 "security": [
                    {"bearerAuth": [] }
                ],
                "requestBody": {
                    "required": true,
                    "content": {
                        "application/json": {
                            "schema": {
                               "type": "object",
                               "required": ["title", "authorId", "year", "genre", "pages", "publisher", "isbn", "place", "language"],
                               "properties": {
                                      "title": {"type": "string"},
                                      "authorId": {"type": "integer"},
                                      "year": {"type": "integer"},
                                      "genre": {"type": "string"},
                                        "pages": {"type": "integer"},
                                        "publisher": {"type": "string"},
                                        "isbn": {"type": "integer"},
                                        "place": {"type": "string"},
                                        "language": {"type": "string"}  
                                 }
                            },
                            "example": {
                                "title": "The Great Adventure",
                                "authorId": 12345,
                                "year": 2022,
                                "genre": "Adventure",
                                "pages": 350,
                                "publisher": "Adventure Press",
                                "isbn": 9781234567890,
                                "place": "New York",
                                "language": "English"
                            }
                        }
                    }
                },
                "responses": {
                    "201": {
                        "description": "Book created successfully"},
                    "400": {
                        "description": "Invalid input"},
                    "500": {
                        "description": "Server error"}
                }
            }
        },
            "/api/books/{id}": {
            "get": {
                "summary": "Get book by ID",
                "tags": ["Books"],
                "parameters": [
                    {
                        "name": "id",
                        "in": "path",
                        "required": true,
                        "schema": {
                            "type": "string"}
                    }
                ],
                "responses": {
                    "200": {
                        "description": "Book details"},
                    "404": {
                        "description": "Book not found"},
                    "500": {
                        "description": "Server error"}
                }
            }
        },
        

            "/books/{id}": {
            "put": {
                "summary": "Update book by ID",
                "tags": ["Books"],
                "parameters": [
                    {
                        "name": "id",
                        "in": "path",
                        "required": true,
                        "schema": {
                            "type": "string"}
                    }
                ],
                "requestBody": {
                    "required": true,
                    "content": {
                        "application/json": {
                            "schema": {
                               "type": "object",
                               "properties": {
                                      "title": {"type": "string"},
                                      "authorId": {"type": "integer"},
                                      "year": {"type": "integer"},
                                      "genre": {"type": "string"},
                                        "pages": {"type": "integer"},
                                        "publisher": {"type": "string"},
                                        "isbn": {"type": "integer"},
                                        "place": {"type": "string"},
                                        "language": {"type": "string"}  
                                 }
                            },
                            "example": {
                                "title": "The Great Adventure - Updated",
                                "authorId": "12345",
                                "year": 2023,
                                "genre": "Adventure",
                                "pages": 400,
                                "publisher": "Adventure Press",
                                "isbn": 9781234567890,
                                "place": "New York",
                                "language": "English"
                            }
                        }
                    }
                },
                "responses": {
                    "200": {
                        "description": "Book updated successfully"},
                    "400": {
                        "description": "Invalid input"},
                    "404": {
                        "description": "Book not found"},
                    "500": {
                        "description": "Server error"}
                }
            },
            "delete": {
                "summary": "Delete book by ID",
                "tags": ["Books"],
                "security": [
                    { "bearerAuth": [] }
                ],
                "parameters": [
                    {
                        "name": "id",
                        "in": "path",
                        "required": true,
                        "schema": {
                            "type": "string"}
                    }
                ],
                "responses": {
                    "204": {
                        "description": "Book deleted successfully"},
                    "404": {
                        "description": "Book not found"},
                    "500": {
                        "description": "Server error"}
                }
            }
        }
    }
}


          